celery_dispatcher/__init__.py
celery_dispatcher/backends.py
celery_dispatcher/core.py
celery_dispatcher/mixins.py
celery_dispatcher/signals.py
celery_dispatcher/states.py
celery_dispatcher/utils.py
celery_dispatcher-1.1.3.dist-info/LICENSE
celery_dispatcher-1.1.3.dist-info/METADATA
celery_dispatcher-1.1.3.dist-info/WHEEL
celery_dispatcher-1.1.3.dist-info/top_level.txt
celery_dispatcher-1.1.3.dist-info/RECORD
