Metadata-Version: 2.1
Name: celery-dispatcher
Version: 1.1.3
Summary: An extension for celery to dispatch large amount of subtasks within a main task
Home-page: https://github.com/gsfish/celery-dispatcher
Author: gsfish
Author-email: root@grassfish.net
License: UNKNOWN
Platform: UNKNOWN
Classifier: Programming Language :: Python :: 3
Classifier: License :: OSI Approved :: Apache Software License
Classifier: Operating System :: OS Independent
Requires-Python: >=3.6
License-File: LICENSE
Requires-Dist: celery (<5)
Requires-Dist: redis
